Workbook

Sheet Assumptions
A1: Simon FCFE DCF — Assumptions
A3: Company | B3: Tesla, Inc.
A4: Ticker | B4: TSLA
A5: Valuation date | B5: 2026-06-01
A7: CAPM — Risk-free rate (Rf) | B7: 0.04
A8: CAPM — Equity risk premium (ERP) | B8: 0.055
A9: Beta | B9: 1.793
A10: Cost of common equity (Ke) | B10: 0.138615
A11: Terminal growth (g) | B11: 0.04
A12: FCFE growth (forecast) | B12: 0.025
A13: Projection years | B13: 5
A14: Base FCFE (avg. historical, $) | B14: 5427500000
A15: Shares outstanding | B15: 3755723871
A16: Current share price ($) | B16: 420.11
A17: Implied price — DCF ($) | B17: 15.33372

Sheet Historical FCFE
A1: Historical FCFE Build (Simon components)
A2: FCFE = Cash from operations + Cash from investing + Increase in debt
A4: Line item ($) | B4: 2022 | C4: 2023 | D4: 2024 | E4: 2025
A5: + Cash from operations | B5: 14724000000 | C5: 13256000000 | D5: 14923000000 | E5: 14747000000
A6: + Cash from investing | B6: -11973000000 | C6: -15584000000 | D6: -18787000000 | E6: -15478000000
A7: + Increase in debt | B7: 0 | C7: 3825000000 | D7: 4050000000 | E7: 1096000000
A8: - Increase in operating cash (MAX(0,-ΔCash)) | B8: 776000000 | C8: 0 | D8: 11000000 | E8: 0
A9: =Simon FCFE (sum) | B9: 2751000000 | C9: 1497000000 | D9: 186000000 | E9: 365000000
A10: Yahoo Free Cash Flow (reference) | B10: 7552000000 | C10: 4357000000 | D10: 3581000000 | E10: 6220000000
A11: FCFE used in valuation model | B11: 7552000000 | C11: 4357000000 | D11: 3581000000 | E11: 6220000000
A12: Average FCFE used as base | B12: 5427500000

Sheet DCF
A1: DCF Valuation
A2: Date of Valuation | B2: 2026-06-01
A3: Cost of Common Equity (Ke) | B3: =Assumptions!B10
B5: FY 2027E | C5: FY 2028E | D5: FY 2029E | E5: FY 2030E | F5: FY 2031E | G5: Terminal year
A6: Free Cash Flow to Common Equity (forecast)
B16: 2027 | C16: 2028 | D16: 2029 | E16: 2030 | F16: 2031
A17: Valuation to Common Equity | H17: Python model (reference)
A18: Free Cash Flow to Common Equity | B18: =Assumptions!B14*(1+Assumptions!B12) | C18: =B18*(1+Assumptions!B12) | D18: =C18*(1+Assumptions!B12) | E18: =D18*(1+Assumptions!B12) | F18: =E18*(1+Assumptions!B12) | G18: =F18 | H18: Projected FCFE ($)
A19: Present Value of FCF | B19: =B18/(1+$B$3)^1 | C19: =C18/(1+$B$3)^2 | D19: =D18/(1+$B$3)^3 | E19: =E18/(1+$B$3)^4 | F19: =F18/(1+$B$3)^5 | H19: 5.5631875e+09
A20: Present Value Beyond 5 Years | B20: =(F18/($B$3-Assumptions!B11))/(1+$B$3)^5 | H20: 5.7022672e+09
A21: Present Value of First 5 Years | B21: =SUM(B19:F19) | H21: 5.8448239e+09 | I21: =Assumptions!B11
A22: Forecast Equity Value Before Time Adj. | B22: =SUM(B20:B21) | H22: 5.9909445e+09
A23: Forecasted Value as of Valuation Date (mid-year adj.) | B23: =B22*(1+B3/2) | H23: 6.1407181e+09
A24: Excess Cash on Valuation Date | B24: 0
A25: Less Value of Contingent Equity Claims | B25: 0
A26: Value Attributable to Common Equity | B26: =B23 | H26: 5.7589217e+10
A27: Common Shares Outstanding | B27: =Assumptions!B15
A28: Forecast Price / Share | B28: =B26/B27 | H28: 15.33372

Sheet DCF Audit
A1: DCF audit trail (computed values)
A3: Line Item | B3: Value / Formula
A4: Model | B4: Simon FCFE DCF (equity value to common shareholders)
A5: Cost of equity (Ke) | B5: 13.86%
A6: Terminal growth (g) | B6: 4.00%
A7: FCFE growth (forecast) | B7: 2.50%
A8: Projection horizon | B8: 5 years
A9: Base FCFE (avg. historical) | B9: $5.43B
A11: Year | B11: Projected FCFE
A12: Year 1 | B12: $5.56B
A13: Year 2 | B13: $5.70B
A14: Year 3 | B14: $5.84B
A15: Year 4 | B15: $5.99B
A16: Year 5 | B16: $6.14B
A18: PV of explicit period (Y1-Y5)
A19: Terminal-year FCFE | B19: $6.39B
A20: Terminal value at Y5 | B20: $64.76B
A21: PV of terminal value
A22: Equity value (pre mid-year adj.) | B22: $53.86B
A23: Mid-year convention adjustment | B23: x (1 + Ke/2) = x 1.0693
A24: Equity value (adjusted) | B24: $57.59B
A25: Shares outstanding | B25: 3755.72M
A26: Implied price per share | B26: $15.33
A27: vs. current price | B27: -96.4%
